trlc/__init__.py
trlc/__main__.py
trlc/ast.py
trlc/errors.py
trlc/lexer.py
trlc/lint.py
trlc/math.py
trlc/nested.py
trlc/parser.py
trlc/trlc.py
trlc/vcg.py
trlc/version.py
trlc-2.0.2.dist-info/licenses/LICENSE
trlc-2.0.2.dist-info/METADATA
trlc-2.0.2.dist-info/WHEEL
trlc-2.0.2.dist-info/entry_points.txt
trlc-2.0.2.dist-info/top_level.txt
trlc-2.0.2.dist-info/RECORD
