Metadata-Version: 2.4
Name: trlc
Version: 2.0.2
Summary: Treat Requirements Like Code
Home-page: https://github.com/bmw-software-engineering/trlc
Author: Bayerische Motoren Werke Aktiengesellschaft (BMW AG)
Author-email: philipp.wullstein-kammler@bmw.de
License: GNU General Public License v3
Project-URL: Bug Tracker, https://github.com/bmw-software-engineering/trlc/issues
Project-URL: Documentation, https://github.com/bmw-software-engineering/trlc#documentation
Project-URL: Source Code, https://github.com/bmw-software-engineering/trlc
Classifier: Development Status :: 5 - Production/Stable
Classifier: Environment :: Console
Classifier: Intended Audience :: Developers
Classifier: License :: OSI Approved :: GNU General Public License v3 or later (GPLv3+)
Classifier: Topic :: Documentation
Classifier: Topic :: Software Development
Requires-Python: >=3.8, <=3.13
License-File: LICENSE
Requires-Dist: PyVCG[api]==1.0.7
Dynamic: author
Dynamic: author-email
Dynamic: classifier
Dynamic: description
Dynamic: description-content-type
Dynamic: home-page
Dynamic: license
Dynamic: license-file
Dynamic: project-url
Dynamic: requires-dist
Dynamic: requires-python
Dynamic: summary
